{
  "hash": "15c9fc9bb974694ceb364f2c0ee742fe",
  "result": {
    "engine": "knitr",
    "markdown": "---\ntitle: \"Dados e Métodos\"\n---\n\n\n::: {.cell layout-align=\"center\"}\n\n```{.r .cell-code}\nlibrary(tidyverse)\nlibrary(DT)\n```\n:::\n\n\n## Objetos carregados\n\n\n::: {.cell layout-align=\"center\"}\n\n```{.r .cell-code}\nls()\n```\n\n::: {.cell-output .cell-output-stdout}\n\n```\ncharacter(0)\n```\n\n\n:::\n:::\n\n\n### Meteorologia (horária)\n\n\n::: {.cell layout-align=\"center\"}\n\n```{.r .cell-code}\nif (exists(\"meteo_hour\")) dplyr::glimpse(meteo_hour)\n```\n:::\n\n\n### Qualidade do ar — diário (GM-5000)\n\n\n::: {.cell layout-align=\"center\"}\n\n```{.r .cell-code}\nif (exists(\"Datafinal\")) dplyr::glimpse(Datafinal)\n```\n:::\n\n\n### Qualidade do ar — horário (GM-5000)\n\n\n::: {.cell layout-align=\"center\"}\n\n```{.r .cell-code}\nif (exists(\"air_quality_data_ugm3\")) dplyr::glimpse(air_quality_data_ugm3)\n```\n:::\n\n\n### PurpleAir (PM2.5 diário corrigido)\n\n\n::: {.cell layout-align=\"center\"}\n\n```{.r .cell-code}\nif (exists(\"purpleair\")) dplyr::glimpse(purpleair)\n```\n:::\n\n\n### Tabelas auxiliares (AQI e precauções)\n\n\n::: {.cell layout-align=\"center\"}\n\n```{.r .cell-code}\nif (exists(\"Poltab\")) head(Poltab)\nif (exists(\"AQItab\")) head(AQItab)\n```\n:::\n\n\n## Diretrizes OMS\n\n\n::: {.cell layout-align=\"center\"}\n\n```{.r .cell-code}\nif (exists(\"who_limit_all\")) who_limit_all\n```\n:::\n\n\n## Nota sobre horários e TZ\n\nTodas as datas são normalizadas para \"America/Sao_Paulo\". Manter consistência é essencial para agregações diárias e cálculo de médias móveis (ex.: O3 8h).\n",
    "supporting": [],
    "filters": [
      "rmarkdown/pagebreak.lua"
    ],
    "includes": {
      "include-in-header": [
        "<link href=\"site_libs/pagedtable-1.1/css/pagedtable.css\" rel=\"stylesheet\" />\n<script src=\"site_libs/pagedtable-1.1/js/pagedtable.js\"></script>\n"
      ]
    },
    "engineDependencies": {},
    "preserve": {},
    "postProcess": true
  }
}